setup.cfg
setup.py
scone_client/__init__.py
scone_client.egg-info/PKG-INFO
scone_client.egg-info/SOURCES.txt
scone_client.egg-info/dependency_links.txt
scone_client.egg-info/top_level.txt